fhirschemapy/__init__.py
fhirschemapy/py.typed
fhirschemapy/R4B/__init__.py
fhirschemapy/R4B/account.py
fhirschemapy/R4B/activity_definition.py
fhirschemapy/R4B/adverse_event.py
fhirschemapy/R4B/allergy_intolerance.py
fhirschemapy/R4B/appointment.py
fhirschemapy/R4B/appointment_response.py
fhirschemapy/R4B/audit_event.py
fhirschemapy/R4B/base.py
fhirschemapy/R4B/basic.py
fhirschemapy/R4B/binary.py
fhirschemapy/R4B/biologically_derived_product.py
fhirschemapy/R4B/body_structure.py
fhirschemapy/R4B/bundle.py
fhirschemapy/R4B/capability_statement.py
fhirschemapy/R4B/care_plan.py
fhirschemapy/R4B/care_team.py
fhirschemapy/R4B/catalog_entry.py
fhirschemapy/R4B/charge_item.py
fhirschemapy/R4B/charge_item_definition.py
fhirschemapy/R4B/claim.py
fhirschemapy/R4B/claim_response.py
fhirschemapy/R4B/clinical_impression.py
fhirschemapy/R4B/code_system.py
fhirschemapy/R4B/communication.py
fhirschemapy/R4B/communication_request.py
fhirschemapy/R4B/compartment_definition.py
fhirschemapy/R4B/composition.py
fhirschemapy/R4B/concept_map.py
fhirschemapy/R4B/condition.py
fhirschemapy/R4B/consent.py
fhirschemapy/R4B/contract.py
fhirschemapy/R4B/coverage.py
fhirschemapy/R4B/coverage_eligibility_request.py
fhirschemapy/R4B/coverage_eligibility_response.py
fhirschemapy/R4B/detected_issue.py
fhirschemapy/R4B/device.py
fhirschemapy/R4B/device_definition.py
fhirschemapy/R4B/device_metric.py
fhirschemapy/R4B/device_request.py
fhirschemapy/R4B/device_use_statement.py
fhirschemapy/R4B/diagnostic_report.py
fhirschemapy/R4B/document_manifest.py
fhirschemapy/R4B/document_reference.py
fhirschemapy/R4B/domain_resource.py
fhirschemapy/R4B/effect_evidence_synthesis.py
fhirschemapy/R4B/encounter.py
fhirschemapy/R4B/endpoint.py
fhirschemapy/R4B/enrollment_request.py
fhirschemapy/R4B/enrollment_response.py
fhirschemapy/R4B/episode_of_care.py
fhirschemapy/R4B/event_definition.py
fhirschemapy/R4B/evidence.py
fhirschemapy/R4B/evidence_variable.py
fhirschemapy/R4B/example_scenario.py
fhirschemapy-0.0.10.dist-info/licenses/LICENSE
fhirschemapy-0.0.10.dist-info/METADATA
fhirschemapy-0.0.10.dist-info/WHEEL
fhirschemapy-0.0.10.dist-info/top_level.txt
fhirschemapy-0.0.10.dist-info/RECORD
