Metadata-Version: 2.4
Name: fhirschemapy
Version: 0.0.10
Summary: fhirschemapy
Home-page: https://github.com/icanbwell/fhir-schema-py
Author: Imran Qureshi
Author-email: imran.qureshi@bwell.com
License: Apache-2.0
Classifier: Development Status :: 4 - Beta
Classifier: Programming Language :: Python :: 3
Classifier: Operating System :: OS Independent
Requires-Python: >=3.10
License-File: LICENSE
Requires-Dist: requests>=2.32.0
Requires-Dist: pydantic<3.0.0,>=2.11.0
Dynamic: author
Dynamic: author-email
Dynamic: classifier
Dynamic: description
Dynamic: description-content-type
Dynamic: home-page
Dynamic: license
Dynamic: license-file
Dynamic: requires-dist
Dynamic: requires-python
Dynamic: summary
